{
    "cul": 1,
    "dataset": "Aminer",
    "device": "cuda:2",
    "dhconfig": "../../logs/run/para/exp/Aminer/archs/0",
    "dynamic": true,
    "epoch": 50,
    "grad_clip": 0,
    "hid_dim": 8,
    "hlinear_act": "tanh",
    "homo": false,
    "in_dim": -1,
    "log_dir": "../../logs/run/para/exp/Aminer/archs/0/33",
    "lr": 0.01,
    "max_epochs": 500,
    "model": "DHSpace",
    "n_heads": 4,
    "n_layers": 2,
    "norm": 1,
    "num_classes": -1,
    "out_dim": 8,
    "patience": 10,
    "predict_type": "author",
    "seed": 33,
    "shuffle": 1,
    "test_auc": 0.8813741968213966,
    "test_full": false,
    "time": 367.9544186592102,
    "time_per_epoch": 7.214792527404486,
    "train_auc": 0.9236940071370207,
    "twin": 8,
    "val_auc": 0.8914293638560129,
    "wd": 0.0
}